{
    "name": "Global Information",
    "numberOfRequests": {
        "total": 500,
        "ok": 500,
        "ko": 0
    },
    "minResponseTime": {
        "total": 16,
        "ok": 16,
        "ko": 0
    },
    "maxResponseTime": {
        "total": 1173,
        "ok": 1173,
        "ko": 0
    },
    "meanResponseTime": {
        "total": 294,
        "ok": 294,
        "ko": 0
    },
    "standardDeviation": {
        "total": 410,
        "ok": 410,
        "ko": 0
    },
    "percentiles1": {
        "total": 66,
        "ok": 66,
        "ko": 0
    },
    "percentiles2": {
        "total": 440,
        "ok": 440,
        "ko": 0
    },
    "percentiles3": {
        "total": 1099,
        "ok": 1099,
        "ko": 0
    },
    "percentiles4": {
        "total": 1118,
        "ok": 1118,
        "ko": 0
    },
    "group1": {
    "name": "t < 500 ms",
    "count": 391,
    "percentage": 78
},
    "group2": {
    "name": "500 ms < t < 1800 ms",
    "count": 109,
    "percentage": 22
},
    "group3": {
    "name": "t > 1800 ms",
    "count": 0,
    "percentage": 0
},
    "group4": {
    "name": "failed",
    "count": 0,
    "percentage": 0
},
    "meanNumberOfRequestsPerSecond": {
        "total": 41.666666666666664,
        "ok": 41.666666666666664,
        "ko": 0
    }
}